{"date_str": "THURSDAY 16 JULY 2026", "generated_utc": "2026-07-16T05:39:09.230666Z", "categories": {"majors": [{"symbol": "EUR/USD", "slug": "eur-usd", "free": true, "free_today": false, "bias": "NEUTRAL", "price": 1.14676, "change_pct": 0.04}, {"symbol": "GBP/USD", "slug": "gbp-usd", "free": true, "free_today": false, "bias": "BULLISH", "price": 1.35379, "change_pct": -0.01}, {"symbol": "USD/JPY", "slug": "usd-jpy", "free": true, "free_today": false, "bias": "BULLISH", "price": 162.14039, "change_pct": -0.03}, {"symbol": "AUD/USD", "slug": "aud-usd", "free": true, "free_today": false, "bias": "NEUTRAL", "price": 0.69971, "change_pct": -0.14}, {"symbol": "USD/CHF", "slug": "usd-chf", "free": true, "free_today": false, "bias": "NEUTRAL", "price": 0.80619, "change_pct": 0.1}, {"symbol": "USD/CAD", "slug": "usd-cad", "free": false, "free_today": false, "bias": "NEUTRAL", "price": 1.40492, "change_pct": 0.05}, {"symbol": "NZD/USD", "slug": "nzd-usd", "free": false, "free_today": false, "bias": "NEUTRAL", "price": 0.58523, "change_pct": 0.04}], "metals": [{"symbol": "XAU/USD", "slug": "xau-usd", "free": true, "free_today": false, "bias": "BEARISH", "price": 4027.86451, "change_pct": -0.8}], "crosses": [{"symbol": "EUR/GBP", "slug": "eur-gbp", "free": true, "free_today": false, "bias": "BEARISH", "price": 0.8472, "change_pct": 0.06}, {"symbol": "GBP/JPY", "slug": "gbp-jpy", "free": true, "free_today": false, "bias": "BULLISH", "price": 219.46088, "change_pct": -0.07}, {"symbol": "EUR/JPY", "slug": "eur-jpy", "free": true, "free_today": false, "bias": "NEUTRAL", "price": 185.90512, "change_pct": -0.01}, {"symbol": "AUD/JPY", "slug": "aud-jpy", "free": true, "free_today": false, "bias": "NEUTRAL", "price": 113.42374, "change_pct": -0.2}, {"symbol": "EUR/AUD", "slug": "eur-aud", "free": true, "free_today": false, "bias": "NEUTRAL", "price": 1.63897, "change_pct": 0.18}, {"symbol": "GBP/CHF", "slug": "gbp-chf", "free": false, "free_today": false, "bias": "BULLISH", "price": 1.09092, "change_pct": 0.05}, {"symbol": "EUR/CHF", "slug": "eur-chf", "free": false, "free_today": false, "bias": "BULLISH", "price": 0.92429, "change_pct": 0.12}, {"symbol": "CAD/JPY", "slug": "cad-jpy", "free": false, "free_today": false, "bias": "NEUTRAL", "price": 115.38537, "change_pct": -0.11}, {"symbol": "CHF/JPY", "slug": "chf-jpy", "free": false, "free_today": false, "bias": "NEUTRAL", "price": 201.12635, "change_pct": -0.14}, {"symbol": "AUD/NZD", "slug": "aud-nzd", "free": false, "free_today": false, "bias": "BEARISH", "price": 1.19557, "change_pct": -0.19}], "exotics": [{"symbol": "USD/MXN", "slug": "usd-mxn", "free": true, "free_today": false, "bias": "NEUTRAL", "price": 17.39304, "change_pct": 0.02}, {"symbol": "USD/ZAR", "slug": "usd-zar", "free": true, "free_today": false, "bias": "BEARISH", "price": 16.33196, "change_pct": 0.03}, {"symbol": "USD/TRY", "slug": "usd-try", "free": true, "free_today": true, "bias": "BULLISH", "price": 47.05152, "change_pct": 0.04}, {"symbol": "USD/SEK", "slug": "usd-sek", "free": false, "free_today": false, "bias": "NEUTRAL", "price": 9.59977, "change_pct": 0.08}, {"symbol": "USD/NOK", "slug": "usd-nok", "free": false, "free_today": false, "bias": "NEUTRAL", "price": 9.67, "change_pct": 0.14}, {"symbol": "USD/PLN", "slug": "usd-pln", "free": false, "free_today": false, "bias": "BULLISH", "price": 3.77233, "change_pct": 0.09}]}}