{"symbol": "USD/CAD", "slug": "usd-cad", "date_str": "Monday 20 July 2026", "bias": "NEUTRAL", "price": 1.40058, "zones": [{"level": 1.42447, "side": "resistance", "touches": 3, "label": "prior reaction zone"}, {"level": 1.41771, "side": "resistance", "touches": 4, "label": "prior reaction zone"}, {"level": 1.38003, "side": "support", "touches": 3, "label": "prior reaction zone"}, {"level": 1.3712, "side": "support", "touches": 3, "label": "prior reaction zone"}], "d1": [{"time": "2026-03-23", "open": 1.37319, "high": 1.37546, "low": 1.36723, "close": 1.37225}, {"time": "2026-03-24", "open": 1.37225, "high": 1.37852, "low": 1.37207, "close": 1.37638}, {"time": "2026-03-25", "open": 1.37638, "high": 1.38198, "low": 1.37426, "close": 1.38152}, {"time": "2026-03-26", "open": 1.38152, "high": 1.3857, "low": 1.38048, "close": 1.38569}, {"time": "2026-03-27", "open": 1.38569, "high": 1.38912, "low": 1.384, "close": 1.38808}, {"time": "2026-03-28", "open": 1.38808, "high": 1.38958, "low": 1.38395, "close": 1.38935}, {"time": "2026-03-29", "open": 1.38931, "high": 1.39078, "low": 1.38395, "close": 1.38842}, {"time": "2026-03-30", "open": 1.38844, "high": 1.39458, "low": 1.38705, "close": 1.39301}, {"time": "2026-03-31", "open": 1.39299, "high": 1.39659, "low": 1.39092, "close": 1.3912}, {"time": "2026-04-01", "open": 1.39119, "high": 1.39176, "low": 1.38724, "close": 1.38848}, {"time": "2026-04-02", "open": 1.38846, "high": 1.3933, "low": 1.38693, "close": 1.39207}, {"time": "2026-04-03", "open": 1.39204, "high": 1.39488, "low": 1.39146, "close": 1.39469}, {"time": "2026-04-04", "open": 1.39467, "high": 1.39485, "low": 1.39347, "close": 1.39436}, {"time": "2026-04-05", "open": 1.39433, "high": 1.39919, "low": 1.39228, "close": 1.39413}, {"time": "2026-04-06", "open": 1.3941, "high": 1.39478, "low": 1.39032, "close": 1.39106}, {"time": "2026-04-07", "open": 1.39102, "high": 1.39301, "low": 1.38861, "close": 1.38861}, {"time": "2026-04-08", "open": 1.38858, "high": 1.38927, "low": 1.38246, "close": 1.38455}, {"time": "2026-04-09", "open": 1.38453, "high": 1.38598, "low": 1.38049, "close": 1.3817}, {"time": "2026-04-10", "open": 1.38168, "high": 1.3845, "low": 1.38004, "close": 1.38423}, {"time": "2026-04-11", "open": 1.38423, "high": 1.38517, "low": 1.38202, "close": 1.38399}, {"time": "2026-04-12", "open": 1.38396, "high": 1.38784, "low": 1.38078, "close": 1.38568}, {"time": "2026-04-13", "open": 1.38557, "high": 1.38774, "low": 1.37866, "close": 1.37936}, {"time": "2026-04-14", "open": 1.37933, "high": 1.37971, "low": 1.37318, "close": 1.37674}, {"time": "2026-04-15", "open": 1.37671, "high": 1.37884, "low": 1.3727, "close": 1.37425}, {"time": "2026-04-16", "open": 1.37423, "high": 1.37428, "low": 1.36954, "close": 1.37038}, {"time": "2026-04-17", "open": 1.37034, "high": 1.37085, "low": 1.36502, "close": 1.36922}, {"time": "2026-04-18", "open": 1.36921, "high": 1.37603, "low": 1.36788, "close": 1.37295}, {"time": "2026-04-19", "open": 1.37317, "high": 1.37984, "low": 1.36747, "close": 1.36845}, {"time": "2026-04-20", "open": 1.36841, "high": 1.37103, "low": 1.36344, "close": 1.3645}, {"time": "2026-04-21", "open": 1.36446, "high": 1.36756, "low": 1.36337, "close": 1.36622}, {"time": "2026-04-22", "open": 1.36616, "high": 1.36746, "low": 1.36445, "close": 1.36722}, {"time": "2026-04-23", "open": 1.36723, "high": 1.37121, "low": 1.36604, "close": 1.36994}, {"time": "2026-04-24", "open": 1.36986, "high": 1.37141, "low": 1.36629, "close": 1.36705}, {"time": "2026-04-25", "open": 1.36702, "high": 1.36807, "low": 1.36663, "close": 1.36753}, {"time": "2026-04-26", "open": 1.36751, "high": 1.36877, "low": 1.36616, "close": 1.36777}, {"time": "2026-04-27", "open": 1.36775, "high": 1.36817, "low": 1.35983, "close": 1.36273}, {"time": "2026-04-28", "open": 1.36273, "high": 1.36917, "low": 1.36134, "close": 1.3684}, {"time": "2026-04-29", "open": 1.36842, "high": 1.37126, "low": 1.36672, "close": 1.36848}, {"time": "2026-04-30", "open": 1.36846, "high": 1.36904, "low": 1.35797, "close": 1.35816}, {"time": "2026-05-01", "open": 1.35822, "high": 1.35932, "low": 1.35503, "close": 1.3592}, {"time": "2026-05-02", "open": 1.35885, "high": 1.35961, "low": 1.3584, "close": 1.35921}, {"time": "2026-05-03", "open": 1.3588, "high": 1.36062, "low": 1.35729, "close": 1.35975}, {"time": "2026-05-04", "open": 1.35897, "high": 1.36274, "low": 1.35756, "close": 1.36253}, {"time": "2026-05-05", "open": 1.36245, "high": 1.36297, "low": 1.36048, "close": 1.36201}, {"time": "2026-05-06", "open": 1.36193, "high": 1.36417, "low": 1.35793, "close": 1.36338}, {"time": "2026-05-07", "open": 1.36337, "high": 1.36653, "low": 1.36204, "close": 1.36648}, {"time": "2026-05-08", "open": 1.36638, "high": 1.37094, "low": 1.36433, "close": 1.36781}, {"time": "2026-05-09", "open": 1.3678, "high": 1.36824, "low": 1.36632, "close": 1.36752}, {"time": "2026-05-10", "open": 1.36752, "high": 1.36896, "low": 1.36578, "close": 1.36742}, {"time": "2026-05-11", "open": 1.36775, "high": 1.36951, "low": 1.36488, "close": 1.36789}, {"time": "2026-05-12", "open": 1.36789, "high": 1.37239, "low": 1.36717, "close": 1.36974}, {"time": "2026-05-13", "open": 1.36973, "high": 1.37185, "low": 1.36847, "close": 1.37069}, {"time": "2026-05-14", "open": 1.37066, "high": 1.37384, "low": 1.37013, "close": 1.37201}, {"time": "2026-05-15", "open": 1.37198, "high": 1.37668, "low": 1.37155, "close": 1.37485}, {"time": "2026-05-16", "open": 1.37486, "high": 1.37549, "low": 1.37486, "close": 1.37513}, {"time": "2026-05-17", "open": 1.37513, "high": 1.37568, "low": 1.37406, "close": 1.37488}, {"time": "2026-05-18", "open": 1.37487, "high": 1.37633, "low": 1.37329, "close": 1.37402}, {"time": "2026-05-19", "open": 1.37398, "high": 1.37749, "low": 1.3736, "close": 1.37445}, {"time": "2026-05-20", "open": 1.37445, "high": 1.37787, "low": 1.37332, "close": 1.37455}, {"time": "2026-05-21", "open": 1.37451, "high": 1.38004, "low": 1.37371, "close": 1.37786}, {"time": "2026-05-22", "open": 1.37787, "high": 1.38229, "low": 1.37742, "close": 1.38195}, {"time": "2026-05-23", "open": 1.382, "high": 1.38282, "low": 1.38128, "close": 1.38202}, {"time": "2026-05-24", "open": 1.38203, "high": 1.38351, "low": 1.37924, "close": 1.3822}, {"time": "2026-05-25", "open": 1.38191, "high": 1.38213, "low": 1.37954, "close": 1.38021}, {"time": "2026-05-26", "open": 1.38023, "high": 1.38213, "low": 1.37985, "close": 1.38142}, {"time": "2026-05-27", "open": 1.38137, "high": 1.38514, "low": 1.38042, "close": 1.38408}, {"time": "2026-05-28", "open": 1.38402, "high": 1.38698, "low": 1.37738, "close": 1.37841}, {"time": "2026-05-29", "open": 1.37842, "high": 1.38291, "low": 1.3772, "close": 1.3797}, {"time": "2026-05-30", "open": 1.37966, "high": 1.38016, "low": 1.37898, "close": 1.37959}, {"time": "2026-05-31", "open": 1.3796, "high": 1.38107, "low": 1.37876, "close": 1.37994}, {"time": "2026-06-01", "open": 1.3799, "high": 1.38487, "low": 1.37899, "close": 1.38412}, {"time": "2026-06-02", "open": 1.38412, "high": 1.38546, "low": 1.3816, "close": 1.38396}, {"time": "2026-06-03", "open": 1.38394, "high": 1.38997, "low": 1.38359, "close": 1.38977}, {"time": "2026-06-04", "open": 1.38978, "high": 1.3925, "low": 1.38815, "close": 1.39106}, {"time": "2026-06-05", "open": 1.39103, "high": 1.39503, "low": 1.38692, "close": 1.39428}, {"time": "2026-06-06", "open": 1.39423, "high": 1.39445, "low": 1.39269, "close": 1.39393}, {"time": "2026-06-07", "open": 1.39393, "high": 1.39479, "low": 1.39137, "close": 1.39393}, {"time": "2026-06-08", "open": 1.39391, "high": 1.39608, "low": 1.39263, "close": 1.39543}, {"time": "2026-06-09", "open": 1.39541, "high": 1.39687, "low": 1.39195, "close": 1.39497}, {"time": "2026-06-10", "open": 1.39498, "high": 1.39571, "low": 1.39011, "close": 1.39445}, {"time": "2026-06-11", "open": 1.39443, "high": 1.40231, "low": 1.39319, "close": 1.39654}, {"time": "2026-06-12", "open": 1.39655, "high": 1.39977, "low": 1.39564, "close": 1.39895}, {"time": "2026-06-13", "open": 1.39901, "high": 1.39939, "low": 1.39829, "close": 1.39901}, {"time": "2026-06-14", "open": 1.39901, "high": 1.40012, "low": 1.39732, "close": 1.39989}, {"time": "2026-06-15", "open": 1.39973, "high": 1.39973, "low": 1.3951, "close": 1.39912}, {"time": "2026-06-16", "open": 1.3991, "high": 1.40186, "low": 1.39801, "close": 1.39952}, {"time": "2026-06-17", "open": 1.39952, "high": 1.41224, "low": 1.39907, "close": 1.41015}, {"time": "2026-06-18", "open": 1.41013, "high": 1.41476, "low": 1.40945, "close": 1.41373}, {"time": "2026-06-19", "open": 1.41377, "high": 1.41834, "low": 1.41276, "close": 1.41556}, {"time": "2026-06-20", "open": 1.41607, "high": 1.41713, "low": 1.41462, "close": 1.41653}, {"time": "2026-06-21", "open": 1.41651, "high": 1.41799, "low": 1.41314, "close": 1.41657}, {"time": "2026-06-22", "open": 1.41647, "high": 1.41934, "low": 1.41473, "close": 1.41607}, {"time": "2026-06-23", "open": 1.41606, "high": 1.42171, "low": 1.4151, "close": 1.421}, {"time": "2026-06-24", "open": 1.42097, "high": 1.42486, "low": 1.42002, "close": 1.42339}, {"time": "2026-06-25", "open": 1.42337, "high": 1.42479, "low": 1.4178, "close": 1.42011}, {"time": "2026-06-26", "open": 1.42008, "high": 1.42092, "low": 1.41693, "close": 1.41942}, {"time": "2026-06-27", "open": 1.41935, "high": 1.42001, "low": 1.41856, "close": 1.4193}, {"time": "2026-06-28", "open": 1.41927, "high": 1.42209, "low": 1.41783, "close": 1.41929}, {"time": "2026-06-29", "open": 1.41926, "high": 1.42177, "low": 1.41759, "close": 1.4212}, {"time": "2026-06-30", "open": 1.42131, "high": 1.42463, "low": 1.41802, "close": 1.41986}, {"time": "2026-07-01", "open": 1.41979, "high": 1.42354, "low": 1.41937, "close": 1.4216}, {"time": "2026-07-02", "open": 1.42152, "high": 1.42246, "low": 1.41526, "close": 1.41811}, {"time": "2026-07-03", "open": 1.41815, "high": 1.42083, "low": 1.41588, "close": 1.42019}, {"time": "2026-07-04", "open": 1.42033, "high": 1.42059, "low": 1.41918, "close": 1.42022}, {"time": "2026-07-05", "open": 1.42019, "high": 1.42101, "low": 1.41859, "close": 1.41968}, {"time": "2026-07-06", "open": 1.41965, "high": 1.42391, "low": 1.41953, "close": 1.42067}, {"time": "2026-07-07", "open": 1.42067, "high": 1.42258, "low": 1.41839, "close": 1.42005}, {"time": "2026-07-08", "open": 1.42005, "high": 1.42104, "low": 1.41551, "close": 1.41746}, {"time": "2026-07-09", "open": 1.41743, "high": 1.41899, "low": 1.41537, "close": 1.41683}, {"time": "2026-07-10", "open": 1.41679, "high": 1.41726, "low": 1.4117, "close": 1.41555}, {"time": "2026-07-11", "open": 1.41559, "high": 1.41733, "low": 1.41525, "close": 1.41583}, {"time": "2026-07-12", "open": 1.4158, "high": 1.41798, "low": 1.4148, "close": 1.41567}, {"time": "2026-07-13", "open": 1.41579, "high": 1.41744, "low": 1.41254, "close": 1.41562}, {"time": "2026-07-14", "open": 1.41564, "high": 1.41574, "low": 1.40482, "close": 1.40607}, {"time": "2026-07-15", "open": 1.40604, "high": 1.40768, "low": 1.4024, "close": 1.40415}, {"time": "2026-07-16", "open": 1.40406, "high": 1.40585, "low": 1.40104, "close": 1.40422}, {"time": "2026-07-17", "open": 1.40417, "high": 1.40487, "low": 1.4006, "close": 1.40213}, {"time": "2026-07-18", "open": 1.40205, "high": 1.40324, "low": 1.4001, "close": 1.40145}, {"time": "2026-07-19", "open": 1.40143, "high": 1.40261, "low": 1.40043, "close": 1.4017}, {"time": "2026-07-20", "open": 1.40174, "high": 1.40232, "low": 1.40056, "close": 1.40058}], "h1": [{"time": "2026-07-15 15:00:00", "open": 1.40491, "high": 1.4053, "low": 1.40476, "close": 1.40524}, {"time": "2026-07-15 16:00:00", "open": 1.40517, "high": 1.4059, "low": 1.40496, "close": 1.4058}, {"time": "2026-07-15 17:00:00", "open": 1.40582, "high": 1.40597, "low": 1.40441, "close": 1.40535}, {"time": "2026-07-15 18:00:00", "open": 1.40532, "high": 1.40581, "low": 1.40462, "close": 1.40555}, {"time": "2026-07-15 19:00:00", "open": 1.40558, "high": 1.40619, "low": 1.40541, "close": 1.40588}, {"time": "2026-07-15 20:00:00", "open": 1.40589, "high": 1.40704, "low": 1.40587, "close": 1.40671}, {"time": "2026-07-15 21:00:00", "open": 1.40669, "high": 1.40722, "low": 1.40643, "close": 1.40682}, {"time": "2026-07-15 22:00:00", "open": 1.40684, "high": 1.40768, "low": 1.40533, "close": 1.40545}, {"time": "2026-07-15 23:00:00", "open": 1.40547, "high": 1.40686, "low": 1.40509, "close": 1.40637}, {"time": "2026-07-16 00:00:00", "open": 1.4064, "high": 1.40693, "low": 1.40509, "close": 1.40513}, {"time": "2026-07-16 01:00:00", "open": 1.40519, "high": 1.40571, "low": 1.40454, "close": 1.40473}, {"time": "2026-07-16 02:00:00", "open": 1.40473, "high": 1.40566, "low": 1.40464, "close": 1.40504}, {"time": "2026-07-16 03:00:00", "open": 1.40519, "high": 1.40519, "low": 1.40315, "close": 1.4032}, {"time": "2026-07-16 04:00:00", "open": 1.40325, "high": 1.40425, "low": 1.4024, "close": 1.40424}, {"time": "2026-07-16 05:00:00", "open": 1.40419, "high": 1.40459, "low": 1.40358, "close": 1.40419}, {"time": "2026-07-16 06:00:00", "open": 1.40416, "high": 1.4046, "low": 1.40386, "close": 1.40415}, {"time": "2026-07-16 07:00:00", "open": 1.40406, "high": 1.40421, "low": 1.40355, "close": 1.40405}, {"time": "2026-07-16 08:00:00", "open": 1.40402, "high": 1.40419, "low": 1.40365, "close": 1.40408}, {"time": "2026-07-16 09:00:00", "open": 1.40408, "high": 1.40411, "low": 1.40352, "close": 1.40369}, {"time": "2026-07-16 10:00:00", "open": 1.40368, "high": 1.40442, "low": 1.40368, "close": 1.40394}, {"time": "2026-07-16 11:00:00", "open": 1.40399, "high": 1.40497, "low": 1.40378, "close": 1.4049}, {"time": "2026-07-16 12:00:00", "open": 1.4049, "high": 1.40536, "low": 1.40489, "close": 1.40509}, {"time": "2026-07-16 13:00:00", "open": 1.40508, "high": 1.40513, "low": 1.40452, "close": 1.40481}, {"time": "2026-07-16 14:00:00", "open": 1.40477, "high": 1.40484, "low": 1.40447, "close": 1.40465}, {"time": "2026-07-16 15:00:00", "open": 1.40466, "high": 1.4051, "low": 1.40447, "close": 1.40506}, {"time": "2026-07-16 16:00:00", "open": 1.40501, "high": 1.40518, "low": 1.40417, "close": 1.4042}, {"time": "2026-07-16 17:00:00", "open": 1.40421, "high": 1.40468, "low": 1.40405, "close": 1.40459}, {"time": "2026-07-16 18:00:00", "open": 1.4046, "high": 1.40493, "low": 1.40422, "close": 1.40423}, {"time": "2026-07-16 19:00:00", "open": 1.40426, "high": 1.40482, "low": 1.40414, "close": 1.40414}, {"time": "2026-07-16 20:00:00", "open": 1.40415, "high": 1.40418, "low": 1.40351, "close": 1.40373}, {"time": "2026-07-16 21:00:00", "open": 1.4037, "high": 1.40384, "low": 1.40311, "close": 1.40341}, {"time": "2026-07-16 22:00:00", "open": 1.4034, "high": 1.4034, "low": 1.40209, "close": 1.40291}, {"time": "2026-07-16 23:00:00", "open": 1.40294, "high": 1.40313, "low": 1.40104, "close": 1.40231}, {"time": "2026-07-17 00:00:00", "open": 1.40229, "high": 1.40339, "low": 1.40193, "close": 1.40327}, {"time": "2026-07-17 01:00:00", "open": 1.40321, "high": 1.40405, "low": 1.40316, "close": 1.40351}, {"time": "2026-07-17 02:00:00", "open": 1.40347, "high": 1.40516, "low": 1.40344, "close": 1.40501}, {"time": "2026-07-17 03:00:00", "open": 1.40497, "high": 1.40585, "low": 1.40497, "close": 1.40532}, {"time": "2026-07-17 04:00:00", "open": 1.40528, "high": 1.40568, "low": 1.40486, "close": 1.40491}, {"time": "2026-07-17 05:00:00", "open": 1.40488, "high": 1.40519, "low": 1.40464, "close": 1.40489}, {"time": "2026-07-17 06:00:00", "open": 1.40486, "high": 1.40529, "low": 1.40408, "close": 1.40422}, {"time": "2026-07-17 07:00:00", "open": 1.40417, "high": 1.40487, "low": 1.40409, "close": 1.4044}, {"time": "2026-07-17 08:00:00", "open": 1.40437, "high": 1.40441, "low": 1.40388, "close": 1.40422}, {"time": "2026-07-17 09:00:00", "open": 1.4042, "high": 1.40428, "low": 1.4037, "close": 1.40392}, {"time": "2026-07-17 10:00:00", "open": 1.40393, "high": 1.40407, "low": 1.40346, "close": 1.40347}, {"time": "2026-07-17 11:00:00", "open": 1.40349, "high": 1.40408, "low": 1.403, "close": 1.40402}, {"time": "2026-07-17 12:00:00", "open": 1.40401, "high": 1.40417, "low": 1.40372, "close": 1.40414}, {"time": "2026-07-17 13:00:00", "open": 1.40409, "high": 1.40415, "low": 1.40365, "close": 1.40369}, {"time": "2026-07-17 14:00:00", "open": 1.40367, "high": 1.40386, "low": 1.4034, "close": 1.4037}, {"time": "2026-07-17 15:00:00", "open": 1.40372, "high": 1.40378, "low": 1.40322, "close": 1.40372}, {"time": "2026-07-17 16:00:00", "open": 1.40368, "high": 1.40403, "low": 1.40291, "close": 1.40318}, {"time": "2026-07-17 17:00:00", "open": 1.40312, "high": 1.40338, "low": 1.40267, "close": 1.40286}, {"time": "2026-07-17 18:00:00", "open": 1.40287, "high": 1.40379, "low": 1.40275, "close": 1.40311}, {"time": "2026-07-17 19:00:00", "open": 1.40306, "high": 1.4036, "low": 1.40297, "close": 1.40308}, {"time": "2026-07-17 20:00:00", "open": 1.40309, "high": 1.4039, "low": 1.40266, "close": 1.40385}, {"time": "2026-07-17 21:00:00", "open": 1.40384, "high": 1.40405, "low": 1.4021, "close": 1.40259}, {"time": "2026-07-17 22:00:00", "open": 1.40255, "high": 1.4029, "low": 1.40206, "close": 1.40278}, {"time": "2026-07-17 23:00:00", "open": 1.40274, "high": 1.40274, "low": 1.40088, "close": 1.40139}, {"time": "2026-07-18 00:00:00", "open": 1.40132, "high": 1.4018, "low": 1.40073, "close": 1.40123}, {"time": "2026-07-18 01:00:00", "open": 1.4011, "high": 1.40193, "low": 1.40077, "close": 1.40159}, {"time": "2026-07-18 02:00:00", "open": 1.40165, "high": 1.40179, "low": 1.4006, "close": 1.40098}, {"time": "2026-07-18 03:00:00", "open": 1.40101, "high": 1.40163, "low": 1.4009, "close": 1.40161}, {"time": "2026-07-18 04:00:00", "open": 1.40158, "high": 1.40166, "low": 1.40093, "close": 1.40117}, {"time": "2026-07-18 05:00:00", "open": 1.40114, "high": 1.40205, "low": 1.40094, "close": 1.40098}, {"time": "2026-07-18 06:00:00", "open": 1.40098, "high": 1.40215, "low": 1.40092, "close": 1.40213}, {"time": "2026-07-18 07:00:00", "open": 1.40205, "high": 1.40324, "low": 1.40081, "close": 1.40228}, {"time": "2026-07-18 08:00:00", "open": 1.40226, "high": 1.40251, "low": 1.40106, "close": 1.40178}, {"time": "2026-07-18 09:00:00", "open": 1.40187, "high": 1.40237, "low": 1.40155, "close": 1.40223}, {"time": "2026-07-18 10:00:00", "open": 1.40223, "high": 1.40231, "low": 1.40079, "close": 1.40131}, {"time": "2026-07-18 11:00:00", "open": 1.40151, "high": 1.4022, "low": 1.40127, "close": 1.40206}, {"time": "2026-07-18 12:00:00", "open": 1.40206, "high": 1.40225, "low": 1.40195, "close": 1.4021}, {"time": "2026-07-18 13:00:00", "open": 1.4021, "high": 1.4022, "low": 1.40191, "close": 1.40206}, {"time": "2026-07-18 14:00:00", "open": 1.40207, "high": 1.4022, "low": 1.40202, "close": 1.40207}, {"time": "2026-07-18 15:00:00", "open": 1.40208, "high": 1.40242, "low": 1.4002, "close": 1.40134}, {"time": "2026-07-18 16:00:00", "open": 1.40148, "high": 1.4023, "low": 1.4001, "close": 1.40206}, {"time": "2026-07-18 17:00:00", "open": 1.40206, "high": 1.40219, "low": 1.40199, "close": 1.40206}, {"time": "2026-07-18 18:00:00", "open": 1.40207, "high": 1.40218, "low": 1.40203, "close": 1.40207}, {"time": "2026-07-18 19:00:00", "open": 1.40207, "high": 1.4022, "low": 1.402, "close": 1.40209}, {"time": "2026-07-18 20:00:00", "open": 1.40207, "high": 1.4022, "low": 1.40201, "close": 1.40209}, {"time": "2026-07-18 21:00:00", "open": 1.40208, "high": 1.40222, "low": 1.40202, "close": 1.40207}, {"time": "2026-07-18 22:00:00", "open": 1.40205, "high": 1.40219, "low": 1.40197, "close": 1.40216}, {"time": "2026-07-18 23:00:00", "open": 1.40213, "high": 1.40217, "low": 1.402, "close": 1.40207}, {"time": "2026-07-19 00:00:00", "open": 1.40205, "high": 1.40222, "low": 1.40194, "close": 1.40214}, {"time": "2026-07-19 01:00:00", "open": 1.40211, "high": 1.40229, "low": 1.40203, "close": 1.40226}, {"time": "2026-07-19 02:00:00", "open": 1.40223, "high": 1.40241, "low": 1.40195, "close": 1.40213}, {"time": "2026-07-19 03:00:00", "open": 1.40214, "high": 1.40228, "low": 1.40187, "close": 1.40217}, {"time": "2026-07-19 04:00:00", "open": 1.40209, "high": 1.4024, "low": 1.40189, "close": 1.40208}, {"time": "2026-07-19 05:00:00", "open": 1.40205, "high": 1.40217, "low": 1.40185, "close": 1.40207}, {"time": "2026-07-19 06:00:00", "open": 1.40205, "high": 1.4022, "low": 1.40075, "close": 1.40145}, {"time": "2026-07-19 07:00:00", "open": 1.40143, "high": 1.40225, "low": 1.40136, "close": 1.40219}, {"time": "2026-07-19 08:00:00", "open": 1.40216, "high": 1.40227, "low": 1.40189, "close": 1.40222}, {"time": "2026-07-19 09:00:00", "open": 1.40219, "high": 1.40231, "low": 1.40196, "close": 1.40229}, {"time": "2026-07-19 10:00:00", "open": 1.40225, "high": 1.40242, "low": 1.40217, "close": 1.40219}, {"time": "2026-07-19 11:00:00", "open": 1.4022, "high": 1.40232, "low": 1.40201, "close": 1.40217}, {"time": "2026-07-19 12:00:00", "open": 1.40217, "high": 1.40222, "low": 1.40202, "close": 1.40205}, {"time": "2026-07-19 13:00:00", "open": 1.40206, "high": 1.40225, "low": 1.40196, "close": 1.40218}, {"time": "2026-07-19 14:00:00", "open": 1.40219, "high": 1.40238, "low": 1.40212, "close": 1.40227}, {"time": "2026-07-19 15:00:00", "open": 1.40228, "high": 1.40244, "low": 1.40226, "close": 1.40237}, {"time": "2026-07-19 16:00:00", "open": 1.40238, "high": 1.40243, "low": 1.40208, "close": 1.40229}, {"time": "2026-07-19 17:00:00", "open": 1.40229, "high": 1.40245, "low": 1.40224, "close": 1.40225}, {"time": "2026-07-19 18:00:00", "open": 1.40226, "high": 1.40243, "low": 1.40224, "close": 1.40236}, {"time": "2026-07-19 19:00:00", "open": 1.40236, "high": 1.40254, "low": 1.40233, "close": 1.40249}, {"time": "2026-07-19 20:00:00", "open": 1.40247, "high": 1.40261, "low": 1.40224, "close": 1.40233}, {"time": "2026-07-19 21:00:00", "open": 1.40232, "high": 1.40238, "low": 1.40217, "close": 1.40228}, {"time": "2026-07-19 22:00:00", "open": 1.40228, "high": 1.40235, "low": 1.40216, "close": 1.40222}, {"time": "2026-07-19 23:00:00", "open": 1.4022, "high": 1.40232, "low": 1.40206, "close": 1.4022}, {"time": "2026-07-20 00:00:00", "open": 1.40218, "high": 1.40223, "low": 1.40043, "close": 1.40048}, {"time": "2026-07-20 01:00:00", "open": 1.40055, "high": 1.4018, "low": 1.40051, "close": 1.40177}, {"time": "2026-07-20 02:00:00", "open": 1.40174, "high": 1.4024, "low": 1.40139, "close": 1.4018}, {"time": "2026-07-20 03:00:00", "open": 1.40177, "high": 1.4022, "low": 1.40144, "close": 1.40215}, {"time": "2026-07-20 04:00:00", "open": 1.40213, "high": 1.40227, "low": 1.40128, "close": 1.40202}, {"time": "2026-07-20 05:00:00", "open": 1.40193, "high": 1.40241, "low": 1.40121, "close": 1.40183}, {"time": "2026-07-20 06:00:00", "open": 1.40184, "high": 1.4024, "low": 1.40128, "close": 1.4017}, {"time": "2026-07-20 07:00:00", "open": 1.40174, "high": 1.40209, "low": 1.40125, "close": 1.40156}, {"time": "2026-07-20 08:00:00", "open": 1.40154, "high": 1.40231, "low": 1.40148, "close": 1.402}, {"time": "2026-07-20 09:00:00", "open": 1.40197, "high": 1.40232, "low": 1.40186, "close": 1.40208}, {"time": "2026-07-20 10:00:00", "open": 1.40206, "high": 1.40206, "low": 1.40134, "close": 1.40137}, {"time": "2026-07-20 11:00:00", "open": 1.40137, "high": 1.40142, "low": 1.40083, "close": 1.40084}, {"time": "2026-07-20 12:00:00", "open": 1.40085, "high": 1.40094, "low": 1.40056, "close": 1.40077}, {"time": "2026-07-20 13:00:00", "open": 1.40072, "high": 1.401, "low": 1.40062, "close": 1.40063}, {"time": "2026-07-20 14:00:00", "open": 1.40067, "high": 1.40084, "low": 1.40056, "close": 1.40058}], "calendar": [], "editorial": "USD/CAD is trading at 1.4006 as the European afternoon session gets underway, sitting at the lower end of a multi-week range and pressing against what has become a notable compression zone just above the 1.4000 handle. The daily chart tells a clear story of distribution: after peaking near 1.4249 in late June, the pair has shed roughly 190 pips across a controlled, grinding decline that has barely paused for breath. Each successive daily candle since mid-July has posted a lower high and a lower close, and the current session is on course to extend that sequence.\n\nThe structure story is one of a market that built a ceiling and then walked away from it. The prior reaction zone around 1.4245 attracted sellers on three separate tests across late June and early July, and that repeated failure to sustain gains above that level effectively confirmed the zone as a meaningful overhead barrier. Below that sits a second resistance cluster near 1.4177, which had offered four touches as a pivot \u2014 it briefly acted as support during the consolidation phase before being surrendered cleanly on 14 July when price broke lower in a single decisive session. That former support is now the more immediate ceiling the pair would need to reclaim to shift the daily narrative. To the downside, the nearest structural reference of note sits considerably lower, around 1.3800, meaning there is relatively open air between current price and the next well-defined support on the daily chart.\n\nThe hourly picture reinforces the cautious tone. Over the past 24 hours, price has drifted in an exceptionally narrow band, rarely straying more than 20 pips from the 1.4020 area. The one notable event was a brief dip to 1.4004 in the early hours of the Asian session, which found buyers quickly enough to suggest some residual demand near the round number. Since then, the recovery has been shallow and unconvincing, with each attempt to push back toward 1.4024 fading. The H1 structure is essentially flat with a slight downward lean, consistent with a market that lacks conviction in either direction but where the path of least resistance remains modestly lower.\n\nThere are no scheduled calendar events today, which means price action is likely to remain technically driven and potentially thin. The absence of catalysts cuts both ways \u2014 it reduces the risk of sharp dislocations, but it also means any directional move that does emerge will be harder to attribute to a fundamental trigger and may prove less sustained.\n\nThe read shifts if price manages a sustained hourly close back above 1.4050 and then reclaims the 1.4080\u20131.4100 area with conviction, which would begin to question the integrity of the current downtrend. A clean break and hold below 1.3990 would, conversely, open the path toward the 1.3800 support cluster in due course.\n\nThis is editorial analysis, not financial advice. Trading involves substantial risk of loss.", "sample": false}